{
  "1": {
    "row": 0,
    "col": 0,
    "src_x": 13.8,
    "src_y": 5.2,
    "dst_x": 546.7,
    "dst_y": 315.5
  },
  "2": {
    "row": 0,
    "col": 1,
    "src_x": 184.24,
    "src_y": 5.2,
    "dst_x": 546.7,
    "dst_y": 315.5
  },
  "3": {
    "row": 0,
    "col": 2,
    "src_x": 354.69,
    "src_y": 5.2,
    "dst_x": 546.7,
    "dst_y": 315.5
  },
  "4": {
    "row": 0,
    "col": 3,
    "src_x": 525.13,
    "src_y": 5.2,
    "dst_x": 546.7,
    "dst_y": 315.5
  },
  "5": {
    "row": 0,
    "col": 4,
    "src_x": 695.57,
    "src_y": 5.2,
    "dst_x": 546.7,
    "dst_y": 315.5
  },
  "6": {
    "row": 0,
    "col": 5,
    "src_x": 866.02,
    "src_y": 5.2,
    "dst_x": 546.7,
    "dst_y": 315.5
  },
  "7": {
    "row": 0,
    "col": 6,
    "src_x": 1036.46,
    "src_y": 5.2,
    "dst_x": 546.7,
    "dst_y": 315.5
  },
  "8": {
    "row": 0,
    "col": 7,
    "src_x": 1206.91,
    "src_y": 5.2,
    "dst_x": 546.7,
    "dst_y": 315.5
  },
  "9": {
    "row": 0,
    "col": 8,
    "src_x": 1377.35,
    "src_y": 5.2,
    "dst_x": 546.7,
    "dst_y": 315.5
  },
  "10": {
    "row": 0,
    "col": 9,
    "src_x": 1547.79,
    "src_y": 5.2,
    "dst_x": 546.7,
    "dst_y": 315.5
  },
  "11": {
    "row": 0,
    "col": 10,
    "src_x": 1718.24,
    "src_y": 5.2,
    "dst_x": 546.7,
    "dst_y": 315.5
  },
  "12": {
    "row": 0,
    "col": 11,
    "src_x": 1888.68,
    "src_y": 5.2,
    "dst_x": 546.7,
    "dst_y": 315.5
  },
  "13": {
    "row": 0,
    "col": 12,
    "src_x": 2059.12,
    "src_y": 5.2,
    "dst_x": 546.7,
    "dst_y": 315.5
  },
  "14": {
    "row": 0,
    "col": 13,
    "src_x": 2229.57,
    "src_y": 5.2,
    "dst_x": 546.7,
    "dst_y": 315.5
  },
  "15": {
    "row": 0,
    "col": 14,
    "src_x": 2400.01,
    "src_y": 5.2,
    "dst_x": 546.7,
    "dst_y": 315.5
  },
  "16": {
    "row": 0,
    "col": 15,
    "src_x": 2570.46,
    "src_y": 5.2,
    "dst_x": 546.7,
    "dst_y": 315.5
  },
  "17": {
    "row": 1,
    "col": 0,
    "src_x": 13.8,
    "src_y": 302.63,
    "dst_x": 546.7,
    "dst_y": 315.5
  },
  "18": {
    "row": 1,
    "col": 1,
    "src_x": 184.24,
    "src_y": 302.63,
    "dst_x": 546.7,
    "dst_y": 315.5
  },
  "19": {
    "row": 1,
    "col": 2,
    "src_x": 354.69,
    "src_y": 302.63,
    "dst_x": 546.7,
    "dst_y": 315.5
  },
  "20": {
    "row": 1,
    "col": 3,
    "src_x": 525.13,
    "src_y": 302.63,
    "dst_x": 546.7,
    "dst_y": 315.5
  },
  "21": {
    "row": 1,
    "col": 4,
    "src_x": 695.57,
    "src_y": 302.63,
    "dst_x": 546.7,
    "dst_y": 315.5
  },
  "22": {
    "row": 1,
    "col": 5,
    "src_x": 866.02,
    "src_y": 302.63,
    "dst_x": 546.7,
    "dst_y": 315.5
  },
  "23": {
    "row": 1,
    "col": 6,
    "src_x": 1036.46,
    "src_y": 302.63,
    "dst_x": 546.7,
    "dst_y": 315.5
  },
  "24": {
    "row": 1,
    "col": 7,
    "src_x": 1206.91,
    "src_y": 302.63,
    "dst_x": 546.7,
    "dst_y": 315.5
  },
  "25": {
    "row": 1,
    "col": 8,
    "src_x": 1377.35,
    "src_y": 302.63,
    "dst_x": 546.7,
    "dst_y": 315.5
  },
  "26": {
    "row": 1,
    "col": 9,
    "src_x": 1547.79,
    "src_y": 302.63,
    "dst_x": 546.7,
    "dst_y": 315.5
  },
  "27": {
    "row": 1,
    "col": 10,
    "src_x": 1718.24,
    "src_y": 302.63,
    "dst_x": 546.7,
    "dst_y": 315.5
  },
  "28": {
    "row": 1,
    "col": 11,
    "src_x": 1888.68,
    "src_y": 302.63,
    "dst_x": 546.7,
    "dst_y": 315.5
  },
  "29": {
    "row": 1,
    "col": 12,
    "src_x": 2059.12,
    "src_y": 302.63,
    "dst_x": 546.7,
    "dst_y": 315.5
  },
  "30": {
    "row": 1,
    "col": 13,
    "src_x": 2229.57,
    "src_y": 302.63,
    "dst_x": 546.7,
    "dst_y": 315.5
  },
  "31": {
    "row": 1,
    "col": 14,
    "src_x": 2400.01,
    "src_y": 302.63,
    "dst_x": 546.7,
    "dst_y": 315.5
  },
  "32": {
    "row": 1,
    "col": 15,
    "src_x": 2570.46,
    "src_y": 302.63,
    "dst_x": 546.7,
    "dst_y": 315.5
  },
  "33": {
    "row": 2,
    "col": 0,
    "src_x": 13.8,
    "src_y": 600.06,
    "dst_x": 546.7,
    "dst_y": 315.5
  },
  "34": {
    "row": 2,
    "col": 1,
    "src_x": 184.24,
    "src_y": 600.06,
    "dst_x": 546.7,
    "dst_y": 315.5
  },
  "35": {
    "row": 2,
    "col": 2,
    "src_x": 354.69,
    "src_y": 600.06,
    "dst_x": 546.7,
    "dst_y": 315.5
  },
  "36": {
    "row": 2,
    "col": 3,
    "src_x": 525.13,
    "src_y": 600.06,
    "dst_x": 546.7,
    "dst_y": 315.5
  },
  "37": {
    "row": 2,
    "col": 4,
    "src_x": 695.57,
    "src_y": 600.06,
    "dst_x": 546.7,
    "dst_y": 315.5
  },
  "38": {
    "row": 2,
    "col": 5,
    "src_x": 866.02,
    "src_y": 600.06,
    "dst_x": 546.7,
    "dst_y": 315.5
  },
  "39": {
    "row": 2,
    "col": 6,
    "src_x": 1036.46,
    "src_y": 600.06,
    "dst_x": 546.7,
    "dst_y": 315.5
  },
  "40": {
    "row": 2,
    "col": 7,
    "src_x": 1206.91,
    "src_y": 600.06,
    "dst_x": 546.7,
    "dst_y": 315.5
  },
  "41": {
    "row": 2,
    "col": 8,
    "src_x": 1377.35,
    "src_y": 600.06,
    "dst_x": 546.7,
    "dst_y": 315.5
  },
  "42": {
    "row": 2,
    "col": 9,
    "src_x": 1547.79,
    "src_y": 600.06,
    "dst_x": 546.7,
    "dst_y": 315.5
  },
  "43": {
    "row": 2,
    "col": 10,
    "src_x": 1718.24,
    "src_y": 600.06,
    "dst_x": 546.7,
    "dst_y": 315.5
  },
  "44": {
    "row": 2,
    "col": 11,
    "src_x": 1888.68,
    "src_y": 600.06,
    "dst_x": 546.7,
    "dst_y": 315.5
  },
  "45": {
    "row": 2,
    "col": 12,
    "src_x": 2059.12,
    "src_y": 600.06,
    "dst_x": 546.7,
    "dst_y": 315.5
  },
  "46": {
    "row": 2,
    "col": 13,
    "src_x": 2229.57,
    "src_y": 600.06,
    "dst_x": 546.7,
    "dst_y": 315.5
  },
  "47": {
    "row": 2,
    "col": 14,
    "src_x": 2400.01,
    "src_y": 600.06,
    "dst_x": 546.7,
    "dst_y": 315.5
  },
  "48": {
    "row": 2,
    "col": 15,
    "src_x": 2570.46,
    "src_y": 600.06,
    "dst_x": 546.7,
    "dst_y": 315.5
  },
  "49": {
    "row": 3,
    "col": 0,
    "src_x": 13.8,
    "src_y": 897.49,
    "dst_x": 546.7,
    "dst_y": 315.5
  },
  "50": {
    "row": 3,
    "col": 1,
    "src_x": 184.24,
    "src_y": 897.49,
    "dst_x": 546.7,
    "dst_y": 315.5
  },
  "51": {
    "row": 3,
    "col": 2,
    "src_x": 354.69,
    "src_y": 897.49,
    "dst_x": 546.7,
    "dst_y": 315.5
  },
  "52": {
    "row": 3,
    "col": 3,
    "src_x": 525.13,
    "src_y": 897.49,
    "dst_x": 546.7,
    "dst_y": 315.5
  },
  "53": {
    "row": 3,
    "col": 4,
    "src_x": 695.57,
    "src_y": 897.49,
    "dst_x": 546.7,
    "dst_y": 315.5
  },
  "54": {
    "row": 3,
    "col": 5,
    "src_x": 866.02,
    "src_y": 897.49,
    "dst_x": 546.7,
    "dst_y": 315.5
  },
  "55": {
    "row": 3,
    "col": 6,
    "src_x": 1036.46,
    "src_y": 897.49,
    "dst_x": 546.7,
    "dst_y": 315.5
  },
  "56": {
    "row": 3,
    "col": 7,
    "src_x": 1206.91,
    "src_y": 897.49,
    "dst_x": 546.7,
    "dst_y": 315.5
  },
  "57": {
    "row": 3,
    "col": 8,
    "src_x": 1377.35,
    "src_y": 897.49,
    "dst_x": 546.7,
    "dst_y": 315.5
  },
  "58": {
    "row": 3,
    "col": 9,
    "src_x": 1547.79,
    "src_y": 897.49,
    "dst_x": 546.7,
    "dst_y": 315.5
  },
  "59": {
    "row": 3,
    "col": 10,
    "src_x": 1718.24,
    "src_y": 897.49,
    "dst_x": 546.7,
    "dst_y": 315.5
  },
  "60": {
    "row": 3,
    "col": 11,
    "src_x": 1888.68,
    "src_y": 897.49,
    "dst_x": 546.7,
    "dst_y": 315.5
  },
  "61": {
    "row": 3,
    "col": 12,
    "src_x": 2059.12,
    "src_y": 897.49,
    "dst_x": 546.7,
    "dst_y": 315.5
  },
  "62": {
    "row": 3,
    "col": 13,
    "src_x": 2229.57,
    "src_y": 897.49,
    "dst_x": 546.7,
    "dst_y": 315.5
  },
  "63": {
    "row": 3,
    "col": 14,
    "src_x": 2400.01,
    "src_y": 897.49,
    "dst_x": 546.7,
    "dst_y": 315.5
  },
  "64": {
    "row": 3,
    "col": 15,
    "src_x": 2570.46,
    "src_y": 897.49,
    "dst_x": 546.7,
    "dst_y": 315.5
  },
  "65": {
    "row": 4,
    "col": 0,
    "src_x": 13.8,
    "src_y": 1194.93,
    "dst_x": 546.7,
    "dst_y": 315.5
  },
  "66": {
    "row": 4,
    "col": 1,
    "src_x": 184.24,
    "src_y": 1194.93,
    "dst_x": 546.7,
    "dst_y": 315.5
  },
  "67": {
    "row": 4,
    "col": 2,
    "src_x": 354.69,
    "src_y": 1194.93,
    "dst_x": 546.7,
    "dst_y": 315.5
  },
  "68": {
    "row": 4,
    "col": 3,
    "src_x": 525.13,
    "src_y": 1194.93,
    "dst_x": 546.7,
    "dst_y": 315.5
  },
  "69": {
    "row": 4,
    "col": 4,
    "src_x": 695.57,
    "src_y": 1194.93,
    "dst_x": 546.7,
    "dst_y": 315.5
  },
  "70": {
    "row": 4,
    "col": 5,
    "src_x": 866.02,
    "src_y": 1194.93,
    "dst_x": 546.7,
    "dst_y": 315.5
  },
  "71": {
    "row": 4,
    "col": 6,
    "src_x": 1036.46,
    "src_y": 1194.93,
    "dst_x": 546.7,
    "dst_y": 315.5
  },
  "72": {
    "row": 4,
    "col": 7,
    "src_x": 1206.91,
    "src_y": 1194.93,
    "dst_x": 546.7,
    "dst_y": 315.5
  },
  "73": {
    "row": 4,
    "col": 8,
    "src_x": 1377.35,
    "src_y": 1194.93,
    "dst_x": 546.7,
    "dst_y": 315.5
  },
  "74": {
    "row": 4,
    "col": 9,
    "src_x": 1547.79,
    "src_y": 1194.93,
    "dst_x": 546.7,
    "dst_y": 315.5
  },
  "75": {
    "row": 4,
    "col": 10,
    "src_x": 1718.24,
    "src_y": 1194.93,
    "dst_x": 546.7,
    "dst_y": 315.5
  },
  "76": {
    "row": 4,
    "col": 11,
    "src_x": 1888.68,
    "src_y": 1194.93,
    "dst_x": 546.7,
    "dst_y": 315.5
  },
  "77": {
    "row": 4,
    "col": 12,
    "src_x": 2059.12,
    "src_y": 1194.93,
    "dst_x": 546.7,
    "dst_y": 315.5
  },
  "78": {
    "row": 4,
    "col": 13,
    "src_x": 2229.57,
    "src_y": 1194.93,
    "dst_x": 546.7,
    "dst_y": 315.5
  },
  "79": {
    "row": 4,
    "col": 14,
    "src_x": 2400.01,
    "src_y": 1194.93,
    "dst_x": 546.7,
    "dst_y": 315.5
  },
  "80": {
    "row": 4,
    "col": 15,
    "src_x": 2570.46,
    "src_y": 1194.93,
    "dst_x": 546.7,
    "dst_y": 315.5
  },
  "81": {
    "row": 5,
    "col": 0,
    "src_x": 13.8,
    "src_y": 1492.36,
    "dst_x": 546.7,
    "dst_y": 315.5
  },
  "82": {
    "row": 5,
    "col": 1,
    "src_x": 184.24,
    "src_y": 1492.36,
    "dst_x": 546.7,
    "dst_y": 315.5
  },
  "83": {
    "row": 5,
    "col": 2,
    "src_x": 354.69,
    "src_y": 1492.36,
    "dst_x": 546.7,
    "dst_y": 315.5
  },
  "84": {
    "row": 5,
    "col": 3,
    "src_x": 525.13,
    "src_y": 1492.36,
    "dst_x": 546.7,
    "dst_y": 315.5
  },
  "85": {
    "row": 5,
    "col": 4,
    "src_x": 695.57,
    "src_y": 1492.36,
    "dst_x": 546.7,
    "dst_y": 315.5
  },
  "86": {
    "row": 5,
    "col": 5,
    "src_x": 866.02,
    "src_y": 1492.36,
    "dst_x": 546.7,
    "dst_y": 315.5
  },
  "87": {
    "row": 5,
    "col": 6,
    "src_x": 1036.46,
    "src_y": 1492.36,
    "dst_x": 546.7,
    "dst_y": 315.5
  },
  "88": {
    "row": 5,
    "col": 7,
    "src_x": 1206.91,
    "src_y": 1492.36,
    "dst_x": 546.7,
    "dst_y": 315.5
  },
  "89": {
    "row": 5,
    "col": 8,
    "src_x": 1377.35,
    "src_y": 1492.36,
    "dst_x": 546.7,
    "dst_y": 315.5
  },
  "90": {
    "row": 5,
    "col": 9,
    "src_x": 1547.79,
    "src_y": 1492.36,
    "dst_x": 546.7,
    "dst_y": 315.5
  },
  "91": {
    "row": 5,
    "col": 10,
    "src_x": 1718.24,
    "src_y": 1492.36,
    "dst_x": 546.7,
    "dst_y": 315.5
  },
  "92": {
    "row": 5,
    "col": 11,
    "src_x": 1888.68,
    "src_y": 1492.36,
    "dst_x": 546.7,
    "dst_y": 315.5
  },
  "93": {
    "row": 5,
    "col": 12,
    "src_x": 2059.12,
    "src_y": 1492.36,
    "dst_x": 546.7,
    "dst_y": 315.5
  },
  "94": {
    "row": 5,
    "col": 13,
    "src_x": 2229.57,
    "src_y": 1492.36,
    "dst_x": 546.7,
    "dst_y": 315.5
  },
  "95": {
    "row": 5,
    "col": 14,
    "src_x": 2400.01,
    "src_y": 1492.36,
    "dst_x": 546.7,
    "dst_y": 315.5
  },
  "96": {
    "row": 5,
    "col": 15,
    "src_x": 2570.46,
    "src_y": 1492.36,
    "dst_x": 546.7,
    "dst_y": 315.5
  },
  "97": {
    "row": 6,
    "col": 0,
    "src_x": 13.8,
    "src_y": 1789.79,
    "dst_x": 546.7,
    "dst_y": 315.5
  },
  "98": {
    "row": 6,
    "col": 1,
    "src_x": 184.24,
    "src_y": 1789.79,
    "dst_x": 546.7,
    "dst_y": 315.5
  },
  "99": {
    "row": 6,
    "col": 2,
    "src_x": 354.69,
    "src_y": 1789.79,
    "dst_x": 546.7,
    "dst_y": 315.5
  },
  "100": {
    "row": 6,
    "col": 3,
    "src_x": 525.13,
    "src_y": 1789.79,
    "dst_x": 546.7,
    "dst_y": 315.5
  },
  "101": {
    "row": 6,
    "col": 4,
    "src_x": 695.57,
    "src_y": 1789.79,
    "dst_x": 546.7,
    "dst_y": 315.5
  },
  "102": {
    "row": 6,
    "col": 5,
    "src_x": 866.02,
    "src_y": 1789.79,
    "dst_x": 546.7,
    "dst_y": 315.5
  },
  "103": {
    "row": 6,
    "col": 6,
    "src_x": 1036.46,
    "src_y": 1789.79,
    "dst_x": 546.7,
    "dst_y": 315.5
  },
  "104": {
    "row": 6,
    "col": 7,
    "src_x": 1206.91,
    "src_y": 1789.79,
    "dst_x": 546.7,
    "dst_y": 315.5
  },
  "105": {
    "row": 6,
    "col": 8,
    "src_x": 1377.35,
    "src_y": 1789.79,
    "dst_x": 546.7,
    "dst_y": 315.5
  },
  "106": {
    "row": 6,
    "col": 9,
    "src_x": 1547.79,
    "src_y": 1789.79,
    "dst_x": 546.7,
    "dst_y": 315.5
  },
  "107": {
    "row": 6,
    "col": 10,
    "src_x": 1718.24,
    "src_y": 1789.79,
    "dst_x": 546.7,
    "dst_y": 315.5
  },
  "108": {
    "row": 6,
    "col": 11,
    "src_x": 1888.68,
    "src_y": 1789.79,
    "dst_x": 546.7,
    "dst_y": 315.5
  },
  "109": {
    "row": 6,
    "col": 12,
    "src_x": 2059.12,
    "src_y": 1789.79,
    "dst_x": 546.7,
    "dst_y": 315.5
  },
  "110": {
    "row": 6,
    "col": 13,
    "src_x": 2229.57,
    "src_y": 1789.79,
    "dst_x": 546.7,
    "dst_y": 315.5
  },
  "111": {
    "row": 6,
    "col": 14,
    "src_x": 2400.01,
    "src_y": 1789.79,
    "dst_x": 546.7,
    "dst_y": 315.5
  },
  "112": {
    "row": 6,
    "col": 15,
    "src_x": 2570.46,
    "src_y": 1789.79,
    "dst_x": 546.7,
    "dst_y": 315.5
  },
  "113": {
    "row": 7,
    "col": 0,
    "src_x": 13.8,
    "src_y": 2087.22,
    "dst_x": 546.7,
    "dst_y": 315.5
  },
  "114": {
    "row": 7,
    "col": 1,
    "src_x": 184.24,
    "src_y": 2087.22,
    "dst_x": 546.7,
    "dst_y": 315.5
  },
  "115": {
    "row": 7,
    "col": 2,
    "src_x": 354.69,
    "src_y": 2087.22,
    "dst_x": 546.7,
    "dst_y": 315.5
  },
  "116": {
    "row": 7,
    "col": 3,
    "src_x": 525.13,
    "src_y": 2087.22,
    "dst_x": 546.7,
    "dst_y": 315.5
  },
  "117": {
    "row": 7,
    "col": 4,
    "src_x": 695.57,
    "src_y": 2087.22,
    "dst_x": 546.7,
    "dst_y": 315.5
  },
  "118": {
    "row": 7,
    "col": 5,
    "src_x": 866.02,
    "src_y": 2087.22,
    "dst_x": 546.7,
    "dst_y": 315.5
  },
  "119": {
    "row": 7,
    "col": 6,
    "src_x": 1036.46,
    "src_y": 2087.22,
    "dst_x": 546.7,
    "dst_y": 315.5
  },
  "120": {
    "row": 7,
    "col": 7,
    "src_x": 1206.91,
    "src_y": 2087.22,
    "dst_x": 546.7,
    "dst_y": 315.5
  },
  "121": {
    "row": 7,
    "col": 8,
    "src_x": 1377.35,
    "src_y": 2087.22,
    "dst_x": 546.7,
    "dst_y": 315.5
  },
  "122": {
    "row": 7,
    "col": 9,
    "src_x": 1547.79,
    "src_y": 2087.22,
    "dst_x": 546.7,
    "dst_y": 315.5
  },
  "123": {
    "row": 7,
    "col": 10,
    "src_x": 1718.24,
    "src_y": 2087.22,
    "dst_x": 546.7,
    "dst_y": 315.5
  },
  "124": {
    "row": 7,
    "col": 11,
    "src_x": 1888.68,
    "src_y": 2087.22,
    "dst_x": 546.7,
    "dst_y": 315.5
  },
  "125": {
    "row": 7,
    "col": 12,
    "src_x": 2059.12,
    "src_y": 2087.22,
    "dst_x": 546.7,
    "dst_y": 315.5
  },
  "126": {
    "row": 7,
    "col": 13,
    "src_x": 2229.57,
    "src_y": 2087.22,
    "dst_x": 546.7,
    "dst_y": 315.5
  },
  "127": {
    "row": 7,
    "col": 14,
    "src_x": 2400.01,
    "src_y": 2087.22,
    "dst_x": 546.7,
    "dst_y": 315.5
  },
  "128": {
    "row": 7,
    "col": 15,
    "src_x": 2570.46,
    "src_y": 2087.22,
    "dst_x": 546.7,
    "dst_y": 315.5
  },
  "129": {
    "row": 8,
    "col": 0,
    "src_x": 13.8,
    "src_y": 2384.65,
    "dst_x": 546.7,
    "dst_y": 315.5
  },
  "130": {
    "row": 8,
    "col": 1,
    "src_x": 184.24,
    "src_y": 2384.65,
    "dst_x": 546.7,
    "dst_y": 315.5
  },
  "131": {
    "row": 8,
    "col": 2,
    "src_x": 354.69,
    "src_y": 2384.65,
    "dst_x": 546.7,
    "dst_y": 315.5
  },
  "132": {
    "row": 8,
    "col": 3,
    "src_x": 525.13,
    "src_y": 2384.65,
    "dst_x": 546.7,
    "dst_y": 315.5
  },
  "133": {
    "row": 8,
    "col": 4,
    "src_x": 695.57,
    "src_y": 2384.65,
    "dst_x": 546.7,
    "dst_y": 315.5
  },
  "134": {
    "row": 8,
    "col": 5,
    "src_x": 866.02,
    "src_y": 2384.65,
    "dst_x": 546.7,
    "dst_y": 315.5
  },
  "135": {
    "row": 8,
    "col": 6,
    "src_x": 1036.46,
    "src_y": 2384.65,
    "dst_x": 546.7,
    "dst_y": 315.5
  },
  "136": {
    "row": 8,
    "col": 7,
    "src_x": 1206.91,
    "src_y": 2384.65,
    "dst_x": 546.7,
    "dst_y": 315.5
  },
  "137": {
    "row": 8,
    "col": 8,
    "src_x": 1377.35,
    "src_y": 2384.65,
    "dst_x": 546.7,
    "dst_y": 315.5
  },
  "138": {
    "row": 8,
    "col": 9,
    "src_x": 1547.79,
    "src_y": 2384.65,
    "dst_x": 546.7,
    "dst_y": 315.5
  },
  "139": {
    "row": 8,
    "col": 10,
    "src_x": 1718.24,
    "src_y": 2384.65,
    "dst_x": 546.7,
    "dst_y": 315.5
  },
  "140": {
    "row": 8,
    "col": 11,
    "src_x": 1888.68,
    "src_y": 2384.65,
    "dst_x": 546.7,
    "dst_y": 315.5
  },
  "141": {
    "row": 8,
    "col": 12,
    "src_x": 2059.12,
    "src_y": 2384.65,
    "dst_x": 546.7,
    "dst_y": 315.5
  },
  "142": {
    "row": 8,
    "col": 13,
    "src_x": 2229.57,
    "src_y": 2384.65,
    "dst_x": 546.7,
    "dst_y": 315.5
  },
  "143": {
    "row": 8,
    "col": 14,
    "src_x": 2400.01,
    "src_y": 2384.65,
    "dst_x": 546.7,
    "dst_y": 315.5
  },
  "144": {
    "row": 8,
    "col": 15,
    "src_x": 2570.46,
    "src_y": 2384.65,
    "dst_x": 546.7,
    "dst_y": 315.5
  },
  "145": {
    "row": 9,
    "col": 0,
    "src_x": 13.8,
    "src_y": 2682.08,
    "dst_x": 546.7,
    "dst_y": 315.5
  },
  "146": {
    "row": 9,
    "col": 1,
    "src_x": 184.24,
    "src_y": 2682.08,
    "dst_x": 546.7,
    "dst_y": 315.5
  },
  "147": {
    "row": 9,
    "col": 2,
    "src_x": 354.69,
    "src_y": 2682.08,
    "dst_x": 546.7,
    "dst_y": 315.5
  },
  "148": {
    "row": 9,
    "col": 3,
    "src_x": 525.13,
    "src_y": 2682.08,
    "dst_x": 546.7,
    "dst_y": 315.5
  },
  "149": {
    "row": 9,
    "col": 4,
    "src_x": 695.57,
    "src_y": 2682.08,
    "dst_x": 546.7,
    "dst_y": 315.5
  },
  "150": {
    "row": 9,
    "col": 5,
    "src_x": 866.02,
    "src_y": 2682.08,
    "dst_x": 546.7,
    "dst_y": 315.5
  },
  "151": {
    "row": 9,
    "col": 6,
    "src_x": 1036.46,
    "src_y": 2682.08,
    "dst_x": 546.7,
    "dst_y": 315.5
  },
  "152": {
    "row": 9,
    "col": 7,
    "src_x": 1206.91,
    "src_y": 2682.08,
    "dst_x": 546.7,
    "dst_y": 315.5
  },
  "153": {
    "row": 9,
    "col": 8,
    "src_x": 1377.35,
    "src_y": 2682.08,
    "dst_x": 546.7,
    "dst_y": 315.5
  },
  "154": {
    "row": 9,
    "col": 9,
    "src_x": 1547.79,
    "src_y": 2682.08,
    "dst_x": 546.7,
    "dst_y": 315.5
  },
  "155": {
    "row": 9,
    "col": 10,
    "src_x": 1718.24,
    "src_y": 2682.08,
    "dst_x": 546.7,
    "dst_y": 315.5
  },
  "156": {
    "row": 9,
    "col": 11,
    "src_x": 1888.68,
    "src_y": 2682.08,
    "dst_x": 546.7,
    "dst_y": 315.5
  },
  "157": {
    "row": 9,
    "col": 12,
    "src_x": 2059.12,
    "src_y": 2682.08,
    "dst_x": 546.7,
    "dst_y": 315.5
  },
  "158": {
    "row": 9,
    "col": 13,
    "src_x": 2229.57,
    "src_y": 2682.08,
    "dst_x": 546.7,
    "dst_y": 315.5
  },
  "159": {
    "row": 9,
    "col": 14,
    "src_x": 2400.01,
    "src_y": 2682.08,
    "dst_x": 546.7,
    "dst_y": 315.5
  },
  "160": {
    "row": 9,
    "col": 15,
    "src_x": 2570.46,
    "src_y": 2682.08,
    "dst_x": 546.7,
    "dst_y": 315.5
  },
  "161": {
    "row": 10,
    "col": 0,
    "src_x": 13.8,
    "src_y": 2979.51,
    "dst_x": 546.7,
    "dst_y": 315.5
  },
  "162": {
    "row": 10,
    "col": 1,
    "src_x": 184.24,
    "src_y": 2979.51,
    "dst_x": 546.7,
    "dst_y": 315.5
  },
  "163": {
    "row": 10,
    "col": 2,
    "src_x": 354.69,
    "src_y": 2979.51,
    "dst_x": 546.7,
    "dst_y": 315.5
  },
  "164": {
    "row": 10,
    "col": 3,
    "src_x": 525.13,
    "src_y": 2979.51,
    "dst_x": 546.7,
    "dst_y": 315.5
  },
  "165": {
    "row": 10,
    "col": 4,
    "src_x": 695.57,
    "src_y": 2979.51,
    "dst_x": 546.7,
    "dst_y": 315.5
  },
  "166": {
    "row": 10,
    "col": 5,
    "src_x": 866.02,
    "src_y": 2979.51,
    "dst_x": 546.7,
    "dst_y": 315.5
  },
  "167": {
    "row": 10,
    "col": 6,
    "src_x": 1036.46,
    "src_y": 2979.51,
    "dst_x": 546.7,
    "dst_y": 315.5
  },
  "168": {
    "row": 10,
    "col": 7,
    "src_x": 1206.91,
    "src_y": 2979.51,
    "dst_x": 546.7,
    "dst_y": 315.5
  },
  "169": {
    "row": 10,
    "col": 8,
    "src_x": 1377.35,
    "src_y": 2979.51,
    "dst_x": 546.7,
    "dst_y": 315.5
  },
  "170": {
    "row": 10,
    "col": 9,
    "src_x": 1547.79,
    "src_y": 2979.51,
    "dst_x": 546.7,
    "dst_y": 315.5
  },
  "171": {
    "row": 10,
    "col": 10,
    "src_x": 1718.24,
    "src_y": 2979.51,
    "dst_x": 546.7,
    "dst_y": 315.5
  },
  "172": {
    "row": 10,
    "col": 11,
    "src_x": 1888.68,
    "src_y": 2979.51,
    "dst_x": 546.7,
    "dst_y": 315.5
  },
  "173": {
    "row": 10,
    "col": 12,
    "src_x": 2059.12,
    "src_y": 2979.51,
    "dst_x": 546.7,
    "dst_y": 315.5
  },
  "174": {
    "row": 10,
    "col": 13,
    "src_x": 2229.57,
    "src_y": 2979.51,
    "dst_x": 546.7,
    "dst_y": 315.5
  },
  "175": {
    "row": 10,
    "col": 14,
    "src_x": 2400.01,
    "src_y": 2979.51,
    "dst_x": 546.7,
    "dst_y": 315.5
  },
  "176": {
    "row": 10,
    "col": 15,
    "src_x": 2570.46,
    "src_y": 2979.51,
    "dst_x": 546.7,
    "dst_y": 315.5
  },
  "177": {
    "row": 11,
    "col": 0,
    "src_x": 13.8,
    "src_y": 3276.94,
    "dst_x": 546.7,
    "dst_y": 315.5
  },
  "178": {
    "row": 11,
    "col": 1,
    "src_x": 184.24,
    "src_y": 3276.94,
    "dst_x": 546.7,
    "dst_y": 315.5
  },
  "179": {
    "row": 11,
    "col": 2,
    "src_x": 354.69,
    "src_y": 3276.94,
    "dst_x": 546.7,
    "dst_y": 315.5
  },
  "180": {
    "row": 11,
    "col": 3,
    "src_x": 525.13,
    "src_y": 3276.94,
    "dst_x": 546.7,
    "dst_y": 315.5
  },
  "181": {
    "row": 11,
    "col": 4,
    "src_x": 695.57,
    "src_y": 3276.94,
    "dst_x": 546.7,
    "dst_y": 315.5
  },
  "182": {
    "row": 11,
    "col": 5,
    "src_x": 866.02,
    "src_y": 3276.94,
    "dst_x": 546.7,
    "dst_y": 315.5
  },
  "183": {
    "row": 11,
    "col": 6,
    "src_x": 1036.46,
    "src_y": 3276.94,
    "dst_x": 546.7,
    "dst_y": 315.5
  },
  "184": {
    "row": 11,
    "col": 7,
    "src_x": 1206.91,
    "src_y": 3276.94,
    "dst_x": 546.7,
    "dst_y": 315.5
  },
  "185": {
    "row": 11,
    "col": 8,
    "src_x": 1377.35,
    "src_y": 3276.94,
    "dst_x": 546.7,
    "dst_y": 315.5
  },
  "186": {
    "row": 11,
    "col": 9,
    "src_x": 1547.79,
    "src_y": 3276.94,
    "dst_x": 546.7,
    "dst_y": 315.5
  },
  "187": {
    "row": 11,
    "col": 10,
    "src_x": 1718.24,
    "src_y": 3276.94,
    "dst_x": 546.7,
    "dst_y": 315.5
  },
  "188": {
    "row": 11,
    "col": 11,
    "src_x": 1888.68,
    "src_y": 3276.94,
    "dst_x": 546.7,
    "dst_y": 315.5
  },
  "189": {
    "row": 11,
    "col": 12,
    "src_x": 2059.12,
    "src_y": 3276.94,
    "dst_x": 546.7,
    "dst_y": 315.5
  },
  "190": {
    "row": 11,
    "col": 13,
    "src_x": 2229.57,
    "src_y": 3276.94,
    "dst_x": 546.7,
    "dst_y": 315.5
  },
  "191": {
    "row": 11,
    "col": 14,
    "src_x": 2400.01,
    "src_y": 3276.94,
    "dst_x": 546.7,
    "dst_y": 315.5
  },
  "192": {
    "row": 11,
    "col": 15,
    "src_x": 2570.46,
    "src_y": 3276.94,
    "dst_x": 546.7,
    "dst_y": 315.5
  },
  "193": {
    "row": 12,
    "col": 0,
    "src_x": 13.8,
    "src_y": 3574.38,
    "dst_x": 546.7,
    "dst_y": 315.5
  },
  "194": {
    "row": 12,
    "col": 1,
    "src_x": 184.24,
    "src_y": 3574.38,
    "dst_x": 546.7,
    "dst_y": 315.5
  },
  "195": {
    "row": 12,
    "col": 2,
    "src_x": 354.69,
    "src_y": 3574.38,
    "dst_x": 546.7,
    "dst_y": 315.5
  },
  "196": {
    "row": 12,
    "col": 3,
    "src_x": 525.13,
    "src_y": 3574.38,
    "dst_x": 546.7,
    "dst_y": 315.5
  },
  "197": {
    "row": 12,
    "col": 4,
    "src_x": 695.57,
    "src_y": 3574.38,
    "dst_x": 546.7,
    "dst_y": 315.5
  },
  "198": {
    "row": 12,
    "col": 5,
    "src_x": 866.02,
    "src_y": 3574.38,
    "dst_x": 546.7,
    "dst_y": 315.5
  },
  "199": {
    "row": 12,
    "col": 6,
    "src_x": 1036.46,
    "src_y": 3574.38,
    "dst_x": 546.7,
    "dst_y": 315.5
  },
  "200": {
    "row": 12,
    "col": 7,
    "src_x": 1206.91,
    "src_y": 3574.38,
    "dst_x": 546.7,
    "dst_y": 315.5
  },
  "201": {
    "row": 12,
    "col": 8,
    "src_x": 1377.35,
    "src_y": 3574.38,
    "dst_x": 546.7,
    "dst_y": 315.5
  },
  "202": {
    "row": 12,
    "col": 9,
    "src_x": 1547.79,
    "src_y": 3574.38,
    "dst_x": 546.7,
    "dst_y": 315.5
  },
  "203": {
    "row": 12,
    "col": 10,
    "src_x": 1718.24,
    "src_y": 3574.38,
    "dst_x": 546.7,
    "dst_y": 315.5
  },
  "204": {
    "row": 12,
    "col": 11,
    "src_x": 1888.68,
    "src_y": 3574.38,
    "dst_x": 546.7,
    "dst_y": 315.5
  },
  "205": {
    "row": 12,
    "col": 12,
    "src_x": 2059.12,
    "src_y": 3574.38,
    "dst_x": 546.7,
    "dst_y": 315.5
  },
  "206": {
    "row": 12,
    "col": 13,
    "src_x": 2229.57,
    "src_y": 3574.38,
    "dst_x": 546.7,
    "dst_y": 315.5
  },
  "207": {
    "row": 12,
    "col": 14,
    "src_x": 2400.01,
    "src_y": 3574.38,
    "dst_x": 546.7,
    "dst_y": 315.5
  },
  "208": {
    "row": 12,
    "col": 15,
    "src_x": 2570.46,
    "src_y": 3574.38,
    "dst_x": 546.7,
    "dst_y": 315.5
  },
  "209": {
    "row": 13,
    "col": 0,
    "src_x": 13.8,
    "src_y": 3871.81,
    "dst_x": 546.7,
    "dst_y": 315.5
  },
  "210": {
    "row": 13,
    "col": 1,
    "src_x": 184.24,
    "src_y": 3871.81,
    "dst_x": 546.7,
    "dst_y": 315.5
  },
  "211": {
    "row": 13,
    "col": 2,
    "src_x": 354.69,
    "src_y": 3871.81,
    "dst_x": 546.7,
    "dst_y": 315.5
  },
  "212": {
    "row": 13,
    "col": 3,
    "src_x": 525.13,
    "src_y": 3871.81,
    "dst_x": 546.7,
    "dst_y": 315.5
  },
  "213": {
    "row": 13,
    "col": 4,
    "src_x": 695.57,
    "src_y": 3871.81,
    "dst_x": 546.7,
    "dst_y": 315.5
  },
  "214": {
    "row": 13,
    "col": 5,
    "src_x": 866.02,
    "src_y": 3871.81,
    "dst_x": 546.7,
    "dst_y": 315.5
  },
  "215": {
    "row": 13,
    "col": 6,
    "src_x": 1036.46,
    "src_y": 3871.81,
    "dst_x": 546.7,
    "dst_y": 315.5
  },
  "216": {
    "row": 13,
    "col": 7,
    "src_x": 1206.91,
    "src_y": 3871.81,
    "dst_x": 546.7,
    "dst_y": 315.5
  },
  "217": {
    "row": 13,
    "col": 8,
    "src_x": 1377.35,
    "src_y": 3871.81,
    "dst_x": 546.7,
    "dst_y": 315.5
  },
  "218": {
    "row": 13,
    "col": 9,
    "src_x": 1547.79,
    "src_y": 3871.81,
    "dst_x": 546.7,
    "dst_y": 315.5
  },
  "219": {
    "row": 13,
    "col": 10,
    "src_x": 1718.24,
    "src_y": 3871.81,
    "dst_x": 546.7,
    "dst_y": 315.5
  },
  "220": {
    "row": 13,
    "col": 11,
    "src_x": 1888.68,
    "src_y": 3871.81,
    "dst_x": 546.7,
    "dst_y": 315.5
  },
  "221": {
    "row": 13,
    "col": 12,
    "src_x": 2059.12,
    "src_y": 3871.81,
    "dst_x": 546.7,
    "dst_y": 315.5
  },
  "222": {
    "row": 13,
    "col": 13,
    "src_x": 2229.57,
    "src_y": 3871.81,
    "dst_x": 546.7,
    "dst_y": 315.5
  },
  "223": {
    "row": 13,
    "col": 14,
    "src_x": 2400.01,
    "src_y": 3871.81,
    "dst_x": 546.7,
    "dst_y": 315.5
  },
  "224": {
    "row": 13,
    "col": 15,
    "src_x": 2570.46,
    "src_y": 3871.81,
    "dst_x": 546.7,
    "dst_y": 315.5
  },
  "225": {
    "row": 14,
    "col": 0,
    "src_x": 13.8,
    "src_y": 4169.24,
    "dst_x": 546.7,
    "dst_y": 315.5
  },
  "226": {
    "row": 14,
    "col": 1,
    "src_x": 184.24,
    "src_y": 4169.24,
    "dst_x": 546.7,
    "dst_y": 315.5
  },
  "227": {
    "row": 14,
    "col": 2,
    "src_x": 354.69,
    "src_y": 4169.24,
    "dst_x": 546.7,
    "dst_y": 315.5
  },
  "228": {
    "row": 14,
    "col": 3,
    "src_x": 525.13,
    "src_y": 4169.24,
    "dst_x": 546.7,
    "dst_y": 315.5
  },
  "229": {
    "row": 14,
    "col": 4,
    "src_x": 695.57,
    "src_y": 4169.24,
    "dst_x": 546.7,
    "dst_y": 315.5
  },
  "230": {
    "row": 14,
    "col": 5,
    "src_x": 866.02,
    "src_y": 4169.24,
    "dst_x": 546.7,
    "dst_y": 315.5
  },
  "231": {
    "row": 14,
    "col": 6,
    "src_x": 1036.46,
    "src_y": 4169.24,
    "dst_x": 546.7,
    "dst_y": 315.5
  },
  "232": {
    "row": 14,
    "col": 7,
    "src_x": 1206.91,
    "src_y": 4169.24,
    "dst_x": 546.7,
    "dst_y": 315.5
  },
  "233": {
    "row": 14,
    "col": 8,
    "src_x": 1377.35,
    "src_y": 4169.24,
    "dst_x": 546.7,
    "dst_y": 315.5
  },
  "234": {
    "row": 14,
    "col": 9,
    "src_x": 1547.79,
    "src_y": 4169.24,
    "dst_x": 546.7,
    "dst_y": 315.5
  },
  "235": {
    "row": 14,
    "col": 10,
    "src_x": 1718.24,
    "src_y": 4169.24,
    "dst_x": 546.7,
    "dst_y": 315.5
  },
  "236": {
    "row": 14,
    "col": 11,
    "src_x": 1888.68,
    "src_y": 4169.24,
    "dst_x": 546.7,
    "dst_y": 315.5
  },
  "237": {
    "row": 14,
    "col": 12,
    "src_x": 2059.12,
    "src_y": 4169.24,
    "dst_x": 546.7,
    "dst_y": 315.5
  },
  "238": {
    "row": 14,
    "col": 13,
    "src_x": 2229.57,
    "src_y": 4169.24,
    "dst_x": 546.7,
    "dst_y": 315.5
  },
  "239": {
    "row": 14,
    "col": 14,
    "src_x": 2400.01,
    "src_y": 4169.24,
    "dst_x": 546.7,
    "dst_y": 315.5
  },
  "240": {
    "row": 14,
    "col": 15,
    "src_x": 2570.46,
    "src_y": 4169.24,
    "dst_x": 546.7,
    "dst_y": 315.5
  },
  "241": {
    "row": 15,
    "col": 0,
    "src_x": 13.8,
    "src_y": 4466.67,
    "dst_x": 546.7,
    "dst_y": 315.5
  },
  "242": {
    "row": 15,
    "col": 1,
    "src_x": 184.24,
    "src_y": 4466.67,
    "dst_x": 546.7,
    "dst_y": 315.5
  },
  "243": {
    "row": 15,
    "col": 2,
    "src_x": 354.69,
    "src_y": 4466.67,
    "dst_x": 546.7,
    "dst_y": 315.5
  },
  "244": {
    "row": 15,
    "col": 3,
    "src_x": 525.13,
    "src_y": 4466.67,
    "dst_x": 546.7,
    "dst_y": 315.5
  },
  "245": {
    "row": 15,
    "col": 4,
    "src_x": 695.57,
    "src_y": 4466.67,
    "dst_x": 546.7,
    "dst_y": 315.5
  },
  "246": {
    "row": 15,
    "col": 5,
    "src_x": 866.02,
    "src_y": 4466.67,
    "dst_x": 546.7,
    "dst_y": 315.5
  },
  "247": {
    "row": 15,
    "col": 6,
    "src_x": 1036.46,
    "src_y": 4466.67,
    "dst_x": 546.7,
    "dst_y": 315.5
  },
  "248": {
    "row": 15,
    "col": 7,
    "src_x": 1206.91,
    "src_y": 4466.67,
    "dst_x": 546.7,
    "dst_y": 315.5
  },
  "249": {
    "row": 15,
    "col": 8,
    "src_x": 1377.35,
    "src_y": 4466.67,
    "dst_x": 546.7,
    "dst_y": 315.5
  },
  "250": {
    "row": 15,
    "col": 9,
    "src_x": 1547.79,
    "src_y": 4466.67,
    "dst_x": 546.7,
    "dst_y": 315.5
  },
  "251": {
    "row": 15,
    "col": 10,
    "src_x": 1718.24,
    "src_y": 4466.67,
    "dst_x": 546.7,
    "dst_y": 315.5
  },
  "252": {
    "row": 15,
    "col": 11,
    "src_x": 1888.68,
    "src_y": 4466.67,
    "dst_x": 546.7,
    "dst_y": 315.5
  },
  "253": {
    "row": 15,
    "col": 12,
    "src_x": 2059.12,
    "src_y": 4466.67,
    "dst_x": 546.7,
    "dst_y": 315.5
  },
  "254": {
    "row": 15,
    "col": 13,
    "src_x": 2229.57,
    "src_y": 4466.67,
    "dst_x": 546.7,
    "dst_y": 315.5
  },
  "255": {
    "row": 15,
    "col": 14,
    "src_x": 2400.01,
    "src_y": 4466.67,
    "dst_x": 546.7,
    "dst_y": 315.5
  },
  "256": {
    "row": 15,
    "col": 15,
    "src_x": 2570.46,
    "src_y": 4466.67,
    "dst_x": 546.7,
    "dst_y": 315.5
  }
}
